kapetanios_test/__init__.py
kapetanios_test/core.py
kapetanios_test-1.0.1.dist-info/licenses/LICENSE
tests/__init__.py
tests/test_kapetanios.py
kapetanios_test-1.0.1.dist-info/METADATA
kapetanios_test-1.0.1.dist-info/WHEEL
kapetanios_test-1.0.1.dist-info/top_level.txt
kapetanios_test-1.0.1.dist-info/RECORD
