Metadata-Version: 2.4
Name: kapetanios-test
Version: 1.0.1
Summary: Unit root test with up to m structural breaks (Kapetanios, 2005)
Home-page: https://github.com/merwanroudane/kapetanios
Author: Dr. Merwan Roudane
Author-email: "Dr. Merwan Roudane" <merwanroudane920@gmail.com>
License: MIT
Project-URL: Homepage, https://github.com/merwanroudane/kapetanios
Project-URL: Documentation, https://github.com/merwanroudane/kapetanios
Project-URL: Repository, https://github.com/merwanroudane/kapetanios
Project-URL: Bug Tracker, https://github.com/merwanroudane/kapetanios/issues
Keywords: econometrics,unit-root,structural-breaks,time-series,kapetanios
Classifier: Development Status :: 4 - Beta
Classifier: Intended Audience :: Science/Research
Classifier: Topic :: Scientific/Engineering :: Mathematics
Classifier: License :: OSI Approved :: MIT License
Classifier: Programming Language :: Python :: 3
Classifier: Programming Language :: Python :: 3.8
Classifier: Programming Language :: Python :: 3.9
Classifier: Programming Language :: Python :: 3.10
Classifier: Programming Language :: Python :: 3.11
Classifier: Operating System :: Microsoft :: Windows
Classifier: Operating System :: POSIX :: Linux
Classifier: Operating System :: MacOS
Requires-Python: >=3.8
License-File: LICENSE
Requires-Dist: numpy>=1.20.0
Requires-Dist: pandas>=1.3.0
Requires-Dist: scipy>=1.7.0
Requires-Dist: statsmodels>=0.13.0
Provides-Extra: dev
Requires-Dist: pytest>=7.0; extra == "dev"
Requires-Dist: pytest-cov>=3.0; extra == "dev"
Requires-Dist: black>=22.0; extra == "dev"
Requires-Dist: flake8>=4.0; extra == "dev"
Requires-Dist: mypy>=0.950; extra == "dev"
Dynamic: author
Dynamic: home-page
Dynamic: license-file
Dynamic: requires-python
